MANIFEST.in
README.md
requirements.txt
setup.py
kick_s3.egg-info/PKG-INFO
kick_s3.egg-info/SOURCES.txt
kick_s3.egg-info/dependency_links.txt
kick_s3.egg-info/requires.txt
kick_s3.egg-info/top_level.txt
kicks3/__init__.py
kicks3/kicks3.py
kicks3/test.py