Metadata-Version: 2.1
Name: kick-s3
Version: 2.1.1
Summary: Recon tool
Home-page: https://github.com/abuvanth/kicks3
Author: Syed Abuthahir
Author-email: developerabu@gmail.com
License: UNKNOWN
Platform: UNKNOWN
Classifier: Programming Language :: Python :: 3
Classifier: License :: OSI Approved :: MIT License
Classifier: Operating System :: OS Independent
